pp3/__init__.py
pp3/_version.py
pp3/tests/__init__.py
pp3/toolkit/__init__.py
pp3/toolkit/auth.py
pp3/toolkit/community.py
pp3/toolkit/resource.py
pp3/toolkit/utils.py
pp3-0.2.1.dist-info/LICENSE.txt
pp3-0.2.1.dist-info/METADATA
pp3-0.2.1.dist-info/WHEEL
pp3-0.2.1.dist-info/top_level.txt
pp3-0.2.1.dist-info/RECORD
